CHANGES.rst
LICENSE.txt
MANIFEST.in
README.rst
fern.py
setup.py
fern.egg-info/PKG-INFO
fern.egg-info/SOURCES.txt
fern.egg-info/dependency_links.txt
fern.egg-info/not-zip-safe
fern.egg-info/top_level.txt