Metadata-Version: 1.1
Name: fern
Version: 0.2
Summary: Read config from the environment.
Home-page: https://github.com/carljm/fern/
Author: Carl Meyer
Author-email: carl@oddbird.net
License: UNKNOWN
Platform: UNKNOWN
Classifier: Development Status :: 3 - Alpha
Classifier: Environment :: Web Environment
Classifier: Intended Audience :: Developers
Classifier: License :: OSI Approved :: BSD License
Classifier: Operating System :: OS Independent
Classifier: Programming Language :: Python
Classifier: Programming Language :: Python :: 3
Classifier: Programming Language :: Python :: 3.5
